{
  "codes": [
    {
      "vipCode": "X9kL3mNo",
      "hasUsed": false
    },
    {
      "vipCode": "PqR7sTuV",
      "hasUsed": false
    },
    {
      "vipCode": "wXyZ4aBc",
      "hasUsed": false
    },
    {
      "vipCode": "DeFgH2iJ",
      "hasUsed": false
    },
    {
      "vipCode": "kLmNo8Pq",
      "hasUsed": false
    },
    {
      "vipCode": "RsTuV1wX",
      "hasUsed": false
    },
    {
      "vipCode": "yZaBc5De",
      "hasUsed": false
    },
    {
      "vipCode": "FgHiJ9kL",
      "hasUsed": false
    },
    {
      "vipCode": "mNoPq3Rs",
      "hasUsed": false
    },
    {
      "vipCode": "TuVwX6yZ",
      "hasUsed": false
    },
    {
      "vipCode": "aBcDe0Fg",
      "hasUsed": false
    },
    {
      "vipCode": "HiJkL4mN",
      "hasUsed": false
    },
    {
      "vipCode": "oPqR2sTu",
      "hasUsed": false
    },
    {
      "vipCode": "VwXyZ7aB",
      "hasUsed": false
    },
    {
      "vipCode": "cDeFg1Hi",
      "hasUsed": false
    },
    {
      "vipCode": "JkLmN5oP",
      "hasUsed": false
    },
    {
      "vipCode": "qRsT8uVw",
      "hasUsed": false
    },
    {
      "vipCode": "XyZaB3cD",
      "hasUsed": false
    },
    {
      "vipCode": "eFgH6iJk",
      "hasUsed": false
    },
    {
      "vipCode": "LmNo9PqR",
      "hasUsed": false
    }
  ]
}